{"lang":"en","content":[[[{"LeS":["Les","Lek","LyX","Luz","L's"]},{"SOmmetS":["summits","Smuts","Semtex","summit's","sonnets"]}],[{"sOaTE":["swath","swat","stay","state","stat"]},{"SOmmm":["Somme","Sammy","Symon","Syman","Sm"]}],[{"UTILISE":["Udell's","Udall's","Udale's","utilize","utilizes"]},{"Entier":["enter","entries","entires","entire","enters"]}],[{"OPEa^T1ONS":["operettas","operetta","operators","operator","operative"]}],[{"@":[]},{"Entier":["enter","entries","entires","entire","enters"]},{"_":[]},{"SOmmet":["summit","summed","sonnet","Sneed","smut"]}],[{"SOm":["Sm","Sim","Sam","Sun","sum"]}],[{"nO":["nu","no","n","NY","NW"]}],[{"":[]},{"@":[]},{"SOmmet":["summit","summed","sonnet","Sneed","smut"]},{"_":[]},{"Entier":["enter","entries","entires","entire","enters"]}],[{"AxIOMES":["axon's","axons","axion's","axions","axiom's"]}],[{"(":[]},{"SOm(i":["sumer","sonar","snore","summer","sooner"]},{")":[]},{")":[]},{"=":[]}],[{"-EC":["EEC","EC","Es","EEOC","EEG"]}],[{"a":["aw","ah","A","aye","awe"]}],[{"Entier":["enter","entries","entires","entire","enters"]}],[{"fgPe":["fishwife"]},{"doun8\"8":["downer","donor","demur","dunner","downier"]},{"88(":[]},{"nc,cC88at@re":["niggard","nickered","negritude","necrotic","niggered"]},{"iu":["ii","i","Io","iii","IE"]},{"dCnifteOn":["dignifies","dignified","disinvest","disinfect","dignifying"]},{"dC8":["dicer","decry","decor","ducker","dozer"]},{"fgpe8":["foxfire","foxfires","fusiform","foxfire's"]},{"uziGmu(iqu8S":[]}],[{"9ruPh88":[]},{"OriCn(8x8":["orisons","orison","origins","origin","organs"]},{"Ou":["OH","OE","O","ow","OOo"]},{"nOn":["nun","non","noun","noon","none"]},{"diBft*nguCr":["dipterous","diopter","defter","dafter","doubter"]},{"8Omme(8":[]},{")un":[]},{"gruphe)":["gruffer","grubber","grouper","groper","gripper"]},{"On":["Ono","ON","on","own","Owen"]},{"iCb":["Iosep","icecap"]}],[{"d(iqucff8)":["doorkeep","dirigible","derisive","dirigibles","derisively"]},{"SOi(":["sour","sore","soar","sir","sari"]},{"Pur":["Pr","purr","pure","Prue","Pru"]},{"dC8":["dicer","decry","decor","ducker","dozer"]},{"nOm6:":["namer","nunnery"]},{"8Dif":[]},{"pGr":["poser","poker","piker","pager","pacer"]},{"dC8":["dicer","decry","decor","ducker","dozer"]},{"nume@rO8q":["numerous","numeric","numerics","numeracy","namer's"]},{"deuzte8mC":["dusters","duster","dexter","dustier","duster's"]},{"8o[ufiOn":[]}],[{"qui":["quo","qua","Que","quay","q"]},{"m(CnuC":["Morgun","morgen","margin","morgen's","Morgen"]},{"ict@@":["Ishtar","isotropy","isotherm","Isidro","Isidoro"]}],[{"'":[]}],[{"LeS":["Les","Lek","LyX","Luz","L's"]},{"grapheS":["graph's","graphs","graphic","grapes","gropes"]},{"OrientdS":["Orient's","Orients","Oriental","Orient","orient's"]}],[{"SORTE":["Surat","Short","Sarto","sword","swart"]},{"Graphe":["graph","grape","Grove","grope","grippe"]}],[{"UTILISE":["Udell's","Udall's","Udale's","utilize","utilizes"]},{"SOmmet)":["symmetry","symmetric","sunder","Sumter","summitry"]},{"Entier":["enter","entries","entires","entire","enters"]},{")":[]},{"BOO]den":["burden","broaden","Borden","burdens","brooding"]}],[{"OPERAIIONS":["O'Brien's","O'Brien","Oberon's","Oberon","oviform"]}],[{"_":[]},{"Graphe":["graph","grape","Grove","grope","grippe"]}],[{"graphe":["graph","grape","grope","grippe","gripe"]},{"_":[]},{"yide":["yd","Yoda","yeti","yet","yawed"]}],[{"&":[]},{"*":[]},{"SO-et":["Sweet","Set","sweet","Swed","suet"]},{"Graphe":["graph","grape","Grove","grope","grippe"]},{"_":[]},{"Graphe":["graph","grape","Grove","grope","grippe"]}],[{"ajouter":["astuter","acuter","accouter","auguster","aster"]},{"_imSOmmet":["incumbent","incomes","incomer","income","imagines"]},{"_":[]}],[{"_":[]},{"_":[]}],[{"":[]},{"SOmmet":["summit","summed","sonnet","Sneed","smut"]},{"SOmmet":["summit","summed","sonnet","Sneed","smut"]},{"Graphe":["graph","grape","Grove","grope","grippe"]},{"_":[]},{"Graphe":["graph","grape","Grove","grope","grippe"]}],[{"a":["aw","ah","A","aye","awe"]},{"jOuter":["jotter","jitter","jittery","jettier","jitterier"]},{"_i)":["Ir","ire","IRA","Ira"]},{"<":[]},{"_":[]},{")":[]},{"_":[]},{">":[]}],[{"_":[]}],[{"@":[]},{".":[]},{"SOmmet":["summit","summed","sonnet","Sneed","smut"]},{"Graphe":["graph","grape","Grove","grope","grippe"]},{"_":[]},{"BOOIden":["Baden","bidden","baden","boatmen","bitumen"]}],[{"eSf":["exp","ESP","esp","expo","espy"]},{"_un_SOmmet":["unjammed","uncomment","unkempt","uncommon","uncomments"]},{"_de":["dye","due","Doe","doe","do"]}],[{"_":[]}],[{"_":[]}],[{"<":[]},{"_":[]},{")":[]},{"_":[]},{">":[]},{"eSt":["ext","est","exit","EST","east"]},{"_un_arC":["unrest","unmarked","unhorse","unawares","unrests"]},{"_de":["dye","due","Doe","doe","do"]}],[{"+":[]},{"+":[]},{"SOmmef":["swampy","swamp","sump","snuff","Snoopy"]},{"SOmmet":["summit","summed","sonnet","Sneed","smut"]},{"Graphe":["graph","grape","Grove","grope","grippe"]},{"_":[]},{"BOOiden":["Baden","bidden","baden","boatmen","bitumen"]}],[{"_":[]}],[{"+":[]},{"de":["dye","due","doe","do","die"]},{"danS":["dank","dang","duns","dunk","dung"]}],[{"+":[]},{",":[]},{"SOmmet":["summit","summed","sonnet","Sneed","smut"]},{"Graphe":["graph","grape","Grove","grope","grippe"]},{"_":[]},{"Entier":["enter","entries","entires","entire","enters"]}],[{"_":[]}],[{"_":[]}],[{"dme_SuCC":["dengues","dengue","dyeing's","dyeing","duns"]},{"_de":["dye","due","Doe","doe","do"]},{"d-S":["dz","dug","d's","doz","DOS"]}],[{"":[]},{"&":[]},{"Entier":["enter","entries","entires","entire","enters"]},{"SOmmet":["summit","summed","sonnet","Sneed","smut"]},{"Graphe":["graph","grape","Grove","grope","grippe"]},{"_":[]},{"SOmmet":["summit","summed","sonnet","Sneed","smut"]}],[{"_":[]}],[{"_":[]}],[{"_":[]}],[{"dm":["dim","dam","dun","doom","don"]},{"-":[]},{"de":["dye","due","doe","do","die"]},{"d-S":["dz","dug","d's","doz","DOS"]}],[{"SOmmet":["summit","summed","sonnet","Sneed","smut"]},{"Graphe":["graph","grape","Grove","grope","grippe"]},{"_":[]},{"Entier":["enter","entries","entires","entire","enters"]}],[{"_":[]}],[{"_":[]}],[{"dme_pred_de":["dumpier","dumper's","dumpers","dumper","Dnepr's"]},{"_":[]},{"danS":["dank","dang","duns","dunk","dung"]}],[{"*":[]},{".":[]},{"Entier":["enter","entries","entires","entire","enters"]},{"SOmmet":["summit","summed","sonnet","Sneed","smut"]},{"Graphe":["graph","grape","Grove","grope","grippe"]},{"_":[]},{"SOmmet":["summit","summed","sonnet","Sneed","smut"]}],[{"_":[]}],[{"_":[]}],[{"_":[]}],[{"":[]},{"":[]},{"SOmmet":["summit","summed","sonnet","Sneed","smut"]},{"Oraphe":["Orv","orb"]},{"_":[]},{"Graphe":["graph","grape","Grove","grope","grippe"]}],[{"retirer":["retiree","retire","retrier","ruttier","rotter"]},{"_imSOmmet":["incumbent","incomes","incomer","income","imagines"]},{"de":["dye","due","doe","do","die"]}],[{"_":[]}],[{"_":[]}],[{"@":[]},{"SOmmet":["summit","summed","sonnet","Sneed","smut"]},{"SOmmet":["summit","summed","sonnet","Sneed","smut"]},{"_":[]},{"Graphe":["graph","grape","Grove","grope","grippe"]}],[{"retirer":["retiree","retire","retrier","ruttier","rotter"]},{"-i)":["Ir","ire","IRA","Ira"]},{"<":[]},{"_":[]},{")":[]},{"_":[]},{">":[]},{"de":["dye","due","doe","do","die"]}],[{"_":[]}],[{"OPE-RAT1ONS":["operators","operator","operative","operation","operating"]},{"(":[]},{"COMPLMENTA1xES":["complimentary","complementary","compliment's","compliments","complimenting"]},{"SUx":["Sax","Sus","SSW","SSS","SSE"]},{"LES":["LyX","Luz","L's","Los","Liz"]},{"Ga^PHES":["Garvy's","Garv's","Garbo's","Grove's","Gropius"]},{"OaIENTkS":["Ont's","Onondaga","Onida's","Oneida's","Oneidas"]},{")":[]}],[{"+":[]},{"+":[]},{"SOmmef":["swampy","swamp","sump","snuff","Snoopy"]},{"Graphe":["graph","grape","Grove","grope","grippe"]},{"_":[]},{"SOmmet":["summit","summed","sonnet","Sneed","smut"]}],[{"premSuCC":["premiums","premixes","premixed","premix","premium's"]}],[{"SuCCSUivant":["sycophant","Squibbing","Sisyphean","sycophants","suspensively"]}],[{"":[]},{".":[]},{"SOmmet":["summit","summed","sonnet","Sneed","smut"]},{"SOmmet":["summit","summed","sonnet","Sneed","smut"]},{"Graphe":["graph","grape","Grove","grope","grippe"]},{"_":[]},{"SOmmet":["summit","summed","sonnet","Sneed","smut"]}],[{"@":[]},{"@":[]},{"SOmmet":["summit","summed","sonnet","Sneed","smut"]},{"SOmmet":["summit","summed","sonnet","Sneed","smut"]},{"Graphe":["graph","grape","Grove","grope","grippe"]},{"_":[]},{"RheI":["Rhee","Rhea","RI","rhea","Rh"]}],[{"COdt":["Ct","Cody","Codi","COD","Cod"]}],[{"":[]},{".":[]},{"SOmmet":["summit","summed","sonnet","Sneed","smut"]},{"SOmmet":["summit","summed","sonnet","Sneed","smut"]},{"Graphe":["graph","grape","Grove","grope","grippe"]},{"_":[]},{"Graphe":["graph","grape","Grove","grope","grippe"]}],[{"a":["aw","ah","A","aye","awe"]},{"jOuter":["jotter","jitter","jittery","jettier","jitterier"]},{"_!:":[]},{"<":[]},{"_":[]},{")":[]},{"_":[]},{">":[]},{"de":["dye","due","doe","do","die"]},{"_":[]},{"5":[]}],[{"_":[]},{"_":[]}],[{"@":[]},{".":[]},{"Oraphe":["Orv","orb"]},{"_":[]},{"Entier":["enter","entries","entires","entire","enters"]}],[{"nb_SOmmetS":["napkin's","napkins","napkin","Novokuznetsk","Novocains"]}],[{"":[]},{"Graphe":["graph","grape","Grove","grope","grippe"]},{"_":[]},{"Entier":["enter","entries","entires","entire","enters"]}],[{"nb-arcS":["nipper's","nippers","nefarious","Nebr's","Nebraska"]}],[{"(":[]}]],[[{"@":[]},{"Entier":["enter","entries","entires","entire","enters"]},{"_":[]},{"SOmmet":["summit","summed","sonnet","Sneed","smut"]}],[{"":[]},{"@":[]},{"SOmmet":["summit","summed","sonnet","Sneed","smut"]},{"_":[]},{"Entier":["enter","entries","entires","entire","enters"]}]],[[{"a":["aw","ah","A","aye","awe"]}]],[[{"'":[]}]],[[{".":[]}]],[[{"_":[]}]],[[{"_":[]},{"_":[]}]],[[{"-":[]}]],[[{".":[]}]],[[{"1":[]}]]]}